wpextract/__init__.py
wpextract/cli/__init__.py
wpextract/cli/_cli.py
wpextract/cli/_download.py
wpextract/cli/_extract.py
wpextract/cli/_shared.py
wpextract/download/ORIGINAL_LICENSE
wpextract/download/__init__.py
wpextract/download/exceptions.py
wpextract/download/exporter.py
wpextract/download/requestsession.py
wpextract/download/utils.py
wpextract/download/wpapi.py
wpextract/downloader.py
wpextract/extract.py
wpextract/extractors/__init__.py
wpextract/extractors/categories.py
wpextract/extractors/data/__init__.py
wpextract/extractors/data/images.py
wpextract/extractors/data/link_resolver.py
wpextract/extractors/data/links.py
wpextract/extractors/io.py
wpextract/extractors/media.py
wpextract/extractors/pages.py
wpextract/extractors/posts.py
wpextract/extractors/tags.py
wpextract/extractors/users.py
wpextract/parse/__init__.py
wpextract/parse/content.py
wpextract/parse/html.py
wpextract/parse/translations/__init__.py
wpextract/parse/translations/_extractor.py
wpextract/parse/translations/_pickers.py
wpextract/parse/translations/_resolver.py
wpextract/py.typed
wpextract/scrape/__init__.py
wpextract/scrape/crawler.py
wpextract/scrape/processor.py
wpextract/scrape/scrape.py
wpextract/util/__init__.py
wpextract/util/file.py
wpextract/util/html.py
wpextract/util/locale.py
wpextract/util/str.py
wpextract-1.1.1.dist-info/LICENSE
wpextract-1.1.1.dist-info/METADATA
wpextract-1.1.1.dist-info/NOTICE
wpextract-1.1.1.dist-info/WHEEL
wpextract-1.1.1.dist-info/entry_points.txt
wpextract-1.1.1.dist-info/RECORD
