Metadata-Version: 2.3
Name: wpextract
Version: 1.1.1
Summary: Create datasets from WordPress sites
License: Apache-2.0
Author: Freddy Heppell
Author-email: f.heppell@sheffield.ac.uk
Requires-Python: >=3.9
Classifier: Development Status :: 5 - Production/Stable
Classifier: Environment :: Console
Classifier: Intended Audience :: Developers
Classifier: Intended Audience :: Science/Research
Classifier: License :: OSI Approved :: Apache Software License
Classifier: Operating System :: OS Independent
Classifier: Programming Language :: Python :: 3
Classifier: Programming Language :: Python :: 3.9
Classifier: Programming Language :: Python :: 3.10
Classifier: Programming Language :: Python :: 3.11
Classifier: Programming Language :: Python :: 3.12
Classifier: Programming Language :: Python :: 3.13
Classifier: Topic :: Software Development :: Libraries :: Python Modules
Requires-Dist: beautifulsoup4 (>=4.12.0)
Requires-Dist: click (>=8.0.1)
Requires-Dist: click-option-group (>=0.5.3)
Requires-Dist: langcodes (>=3.3.0)
Requires-Dist: lxml (>=5.0.0)
Requires-Dist: numpy (>=1.23.0)
Requires-Dist: pandas (>=1.5.2)
Requires-Dist: requests (>=2.32.3)
Requires-Dist: tqdm (>=4.65.0)
Requires-Dist: urllib3 (>1.21.3,<3)
Project-URL: Documentation, https://wpextract.readthedocs.io/
Project-URL: Homepage, https://wpextract.readthedocs.io/
Project-URL: Repository, https://github.com/GateNLP/wpextract
